crystalbuilder/__init__.py
crystalbuilder/bilbao.py
crystalbuilder/convert.py
crystalbuilder/geometry.py
crystalbuilder/lattice.py
crystalbuilder/lumpy_convert.py
crystalbuilder/utils.py
crystalbuilder/vectors.py
crystalbuilder/viewer.py
crystalbuilder/conversions/__init__.py
crystalbuilder/conversions/lumc.py
crystalbuilder/conversions/model.py
crystalbuilder/conversions/t3d.py
crystalbuilder/housekeeping/types.py
crystalbuilder/resources/227-generators.json
crystalbuilder/resources/227-kvec.json
crystalbuilder/simulation/isofreq.py
crystalbuilder/simulation/utils.py
crystalbuilder-0.7.0.dist-info/METADATA
crystalbuilder-0.7.0.dist-info/WHEEL
crystalbuilder-0.7.0.dist-info/licenses/LICENSE
crystalbuilder-0.7.0.dist-info/RECORD
