Metadata-Version: 2.4
Name: crystalbuilder
Version: 0.7.0
Summary: A package for building 3D photonic crystals
Author: Brandon Hacha
License-File: LICENSE
Requires-Dist: beautifulsoup4
Requires-Dist: matplotlib
Requires-Dist: numpy
Requires-Dist: requests
Requires-Dist: scipy
Requires-Dist: vedo
Provides-Extra: full
Requires-Dist: tidy3d; extra == 'full'
